bulk_signals/__init__.py
bulk_signals/apps.py
bulk_signals/signals.py
bulk_signals/tests/__init__.py
bulk_signals/tests/apps.py
bulk_signals/tests/conftest.py
bulk_signals/tests/models.py
bulk_signals/tests/settings.py
bulk_signals/tests/test_skip.py
bulk_signals/tests/tests.py
bulk_signals/tests/migrations/0001_initial.py
bulk_signals/tests/migrations/__init__.py
django_bulk_signals-0.4.2.dist-info/LICENSE
django_bulk_signals-0.4.2.dist-info/METADATA
django_bulk_signals-0.4.2.dist-info/WHEEL
django_bulk_signals-0.4.2.dist-info/top_level.txt
django_bulk_signals-0.4.2.dist-info/RECORD
